structdc/__init__.py
structdc/const.py
structdc-0.0.3.dist-info/LICENSE.txt
structdc-0.0.3.dist-info/METADATA
structdc-0.0.3.dist-info/WHEEL
structdc-0.0.3.dist-info/top_level.txt
structdc-0.0.3.dist-info/RECORD
