Metadata-Version: 2.1
Name: structdc
Version: 0.0.3
Summary: Data class mapper for C structures
Home-page: https://github.com/KnifeMaster007/structdc
Author: Ilia Galkin
Author-email: km@j4u.su
License: MIT
Platform: UNKNOWN
Requires-Python: >=3.7
